schadem_cdk_construct_sfn_test/__init__.py
schadem_cdk_construct_sfn_test/py.typed
schadem_cdk_construct_sfn_test/_jsii/__init__.py
schadem_cdk_construct_sfn_test/_jsii/schadem-cdk-construct-sfn-test@0.0.14.jsii.tgz
schadem_cdk_construct_sfn_test-0.0.14.dist-info/LICENSE
schadem_cdk_construct_sfn_test-0.0.14.dist-info/METADATA
schadem_cdk_construct_sfn_test-0.0.14.dist-info/WHEEL
schadem_cdk_construct_sfn_test-0.0.14.dist-info/top_level.txt
schadem_cdk_construct_sfn_test-0.0.14.dist-info/RECORD
