Metadata-Version: 2.1
Name: schadem-cdk-construct-sfn-test
Version: 0.0.14
Summary: some description
Home-page: https://github.com/45048633+schadem/schadem-cdk-construct-sfn-test.git
Author: Martin Schade<45048633+schadem@users.noreply.github.com>
License: Apache-2.0
Project-URL: Source, https://github.com/45048633+schadem/schadem-cdk-construct-sfn-test.git
Classifier: Intended Audience :: Developers
Classifier: Operating System :: OS Independent
Classifier: Programming Language :: JavaScript
Classifier: Programming Language :: Python :: 3 :: Only
Classifier: Programming Language :: Python :: 3.7
Classifier: Programming Language :: Python :: 3.8
Classifier: Programming Language :: Python :: 3.9
Classifier: Programming Language :: Python :: 3.10
Classifier: Typing :: Typed
Classifier: Development Status :: 5 - Production/Stable
Classifier: License :: OSI Approved
Requires-Python: ~=3.7
License-File: LICENSE
Requires-Dist: aws-cdk-lib (<3.0.0,>=2.1.0)
Requires-Dist: constructs (<11.0.0,>=10.0.5)
Requires-Dist: jsii (<2.0.0,>=1.58.0)
Requires-Dist: publication (>=0.0.3)
